avgcs/__init__.py
avgcs/core.py
avgcs/mapping.py
avgcs/tracking.py
avgcs/utils.py
avgcs-0.1.0.dist-info/licenses/LICENSE
avgcs-0.1.0.dist-info/METADATA
avgcs-0.1.0.dist-info/WHEEL
avgcs-0.1.0.dist-info/entry_points.txt
avgcs-0.1.0.dist-info/top_level.txt
avgcs-0.1.0.dist-info/RECORD
