Metadata-Version: 2.4
Name: avgcs
Version: 0.1.0
Summary: Audio-Visual Game Control System - Real-time motion tracking and game control
Home-page: https://github.com/avgcs/avgcs
Author: AVGCS Team
Author-email: AVGCS Team <team@avgcs.dev>
Maintainer-email: AVGCS Team <team@avgcs.dev>
License-Expression: MIT
Project-URL: Homepage, https://github.com/avgcs/avgcs
Project-URL: Documentation, https://avgcs.readthedocs.io/
Project-URL: Repository, https://github.com/avgcs/avgcs.git
Project-URL: Bug Tracker, https://github.com/avgcs/avgcs/issues
Keywords: motion-tracking,game-control,mediapipe,opencv,computer-vision
Classifier: Development Status :: 3 - Alpha
Classifier: Intended Audience :: Developers
Classifier: Operating System :: OS Independent
Classifier: Programming Language :: Python :: 3
Classifier: Programming Language :: Python :: 3.8
Classifier: Programming Language :: Python :: 3.9
Classifier: Programming Language :: Python :: 3.10
Classifier: Programming Language :: Python :: 3.11
Classifier: Programming Language :: Python :: 3.12
Classifier: Topic :: Games/Entertainment
Classifier: Topic :: Multimedia :: Video
Classifier: Topic :: Scientific/Engineering :: Artificial Intelligence
Requires-Python: >=3.8
License-File: LICENSE
Requires-Dist: opencv-python>=4.5.0
Requires-Dist: numpy>=1.20.0
Requires-Dist: mediapipe>=0.8.0
Provides-Extra: dev
Requires-Dist: pytest>=6.0; extra == "dev"
Requires-Dist: pytest-cov>=2.0; extra == "dev"
Requires-Dist: black>=22.0; extra == "dev"
Requires-Dist: flake8>=4.0; extra == "dev"
Requires-Dist: mypy>=0.900; extra == "dev"
Provides-Extra: demo
Requires-Dist: pygame>=2.0.0; extra == "demo"
Provides-Extra: docs
Requires-Dist: sphinx>=4.0; extra == "docs"
Requires-Dist: sphinx-rtd-theme>=1.0; extra == "docs"
Dynamic: author
Dynamic: home-page
Dynamic: license-file
Dynamic: requires-python
